polyaxon/__init__.py
polyaxon/__main__.py
polyaxon/_dist.py
polyaxon/api.py
polyaxon/cli.py
polyaxon/client.py
polyaxon/docker.py
polyaxon/exceptions.py
polyaxon/fs.py
polyaxon/k8s.py
polyaxon/logger.py
polyaxon/pkg.py
polyaxon/polyaxonfile.py
polyaxon/py.typed
polyaxon/schemas.py
polyaxon/settings.py
polyaxon/types.py
polyaxon/_auxiliaries/__init__.py
polyaxon/_auxiliaries/cleaner.py
polyaxon/_auxiliaries/default_scheduling.py
polyaxon/_auxiliaries/init.py
polyaxon/_auxiliaries/notifier.py
polyaxon/_auxiliaries/sidecar.py
polyaxon/_auxiliaries/tuner.py
polyaxon/_cli/__init__.py
polyaxon/_cli/admin.py
polyaxon/_cli/artifacts.py
polyaxon/_cli/auth.py
polyaxon/_cli/check.py
polyaxon/_cli/completion.py
polyaxon/_cli/components.py
polyaxon/_cli/config.py
polyaxon/_cli/dashboard.py
polyaxon/_cli/errors.py
polyaxon/_cli/init.py
polyaxon/_cli/models.py
polyaxon/_cli/operations.py
polyaxon/_cli/options.py
polyaxon/_cli/port_forward.py
polyaxon/_cli/project_versions.py
polyaxon/_cli/projects.py
polyaxon/_cli/run.py
polyaxon/_cli/session.py
polyaxon/_cli/utils.py
polyaxon/_cli/version.py
polyaxon/_cli/services/__init__.py
polyaxon/_cli/services/agent.py
polyaxon/_cli/services/clean_artifacts.py
polyaxon/_cli/services/docker.py
polyaxon/_cli/services/initializer.py
polyaxon/_cli/services/notifier.py
polyaxon/_cli/services/sidecar.py
polyaxon/_cli/services/tuner.py
polyaxon/_cli/services/wait.py
polyaxon/_client/__init__.py
polyaxon/_client/client.py
polyaxon/_client/impersonate.py
polyaxon/_client/init.py
polyaxon/_client/mixin.py
polyaxon/_client/organization.py
polyaxon/_client/project.py
polyaxon/_client/run.py
polyaxon/_client/store.py
polyaxon/_client/decorators/__init__.py
polyaxon/_client/decorators/client_call_handler.py
polyaxon/_client/decorators/errors.py
polyaxon/_client/decorators/is_managed.py
polyaxon/_client/transport/__init__.py
polyaxon/_client/transport/http_transport.py
polyaxon/_client/transport/periodic_transport.py
polyaxon-2.12.0.dist-info/licenses/LICENSE
polyaxon-2.12.0.dist-info/METADATA
polyaxon-2.12.0.dist-info/WHEEL
polyaxon-2.12.0.dist-info/entry_points.txt
polyaxon-2.12.0.dist-info/top_level.txt
polyaxon-2.12.0.dist-info/RECORD
