Metadata-Version: 2.4
Name: polyaxon
Version: 2.12.0
Summary: Command Line Interface (CLI) and client to interact with Polyaxon API.
Home-page: https://github.com/polyaxon/polyaxon
Author: Polyaxon, Inc.
Author-email: contact@polyaxon.com
Maintainer: Polyaxon, Inc.
Maintainer-email: contact@polyaxon.com
License: Apache 2.0
Keywords: polyaxon,aws,s3,microsoft,azure,google cloud storage,gcs,deep-learning,machine-learning,data-science,neural-networks,artificial-intelligence,ai,reinforcement-learning,kubernetes,aws,microsoft,azure,google cloud,tensorFlow,pytorch
Platform: any
Classifier: Intended Audience :: Information Technology
Classifier: Intended Audience :: System Administrators
Classifier: Intended Audience :: Developers
Classifier: Intended Audience :: Science/Research
Classifier: Operating System :: OS Independent
Classifier: Programming Language :: Python :: 3
Classifier: Programming Language :: Python
Classifier: Topic :: Software Development :: Libraries :: Application Frameworks
Classifier: Topic :: Software Development :: Libraries :: Python Modules
Classifier: Topic :: Software Development :: Libraries
Classifier: Topic :: Software Development
Classifier: Topic :: Scientific/Engineering :: Artificial Intelligence
Classifier: Typing :: Typed
Classifier: Programming Language :: Python :: 3 :: Only
Classifier: Programming Language :: Python :: 3.6
Classifier: Programming Language :: Python :: 3.7
Classifier: Programming Language :: Python :: 3.8
Classifier: Programming Language :: Python :: 3.9
Classifier: Programming Language :: Python :: 3.10
Classifier: Programming Language :: Python :: 3.11
Requires-Python: >=3.8
License-File: LICENSE
Requires-Dist: click<9.0.0,>=7.1.1
Requires-Dist: clipped==0.11.*
Requires-Dist: vents==0.7.*
Requires-Dist: Jinja2<3.1.5,>=2.10.3
Requires-Dist: kubernetes>=10.0.1
Requires-Dist: python-dateutil>=2.7.3
Requires-Dist: pytz>=2019.2
Requires-Dist: PyYAML>=5.1
Requires-Dist: orjson>=3.7
Requires-Dist: psutil>=5.4.7
Requires-Dist: requests>=2.20.1
Requires-Dist: requests-toolbelt>=0.8.0
Requires-Dist: rich>=12.0.0
Requires-Dist: sentry-sdk>=1.2.0
Requires-Dist: urllib3>=1.25.6
Requires-Dist: certifi>=2022.12.7
Requires-Dist: pydantic>=1.10.2
Requires-Dist: traceml==1.2.*
Requires-Dist: hypertune==1.2.*
Provides-Extra: dev
Requires-Dist: moto==5.0.13; extra == "dev"
Provides-Extra: gcs
Requires-Dist: gcsfs; extra == "gcs"
Provides-Extra: s3
Requires-Dist: s3fs; extra == "s3"
Provides-Extra: azure
Requires-Dist: adlfs; extra == "azure"
Provides-Extra: fsspec
Requires-Dist: fsspec; extra == "fsspec"
Provides-Extra: docker
Requires-Dist: docker; extra == "docker"
Provides-Extra: git
Requires-Dist: gitpython; extra == "git"
Provides-Extra: numpy
Requires-Dist: numpy; extra == "numpy"
Provides-Extra: k8s-async
Requires-Dist: kubernetes_asyncio>=28.2.1; extra == "k8s-async"
Requires-Dist: aiohttp>=3.0.0; extra == "k8s-async"
Requires-Dist: anyio; extra == "k8s-async"
Provides-Extra: fs
Requires-Dist: adlfs==2025.8.0; extra == "fs"
Requires-Dist: fsspec==2025.10.0; extra == "fs"
Requires-Dist: gcsfs==2025.10.0; extra == "fs"
Requires-Dist: s3fs==2025.10.0; extra == "fs"
Provides-Extra: init
Requires-Dist: docker; extra == "init"
Requires-Dist: GitPython<3.2.0; extra == "init"
Requires-Dist: aiofiles<=25.1.0; extra == "init"
Provides-Extra: sidecar
Requires-Dist: aiofiles<=25.1.0; extra == "sidecar"
Requires-Dist: pandas; extra == "sidecar"
Requires-Dist: anyio; extra == "sidecar"
Provides-Extra: sandbox
Requires-Dist: haupt[sandbox]; extra == "sandbox"
Dynamic: author
Dynamic: author-email
Dynamic: classifier
Dynamic: description
Dynamic: description-content-type
Dynamic: home-page
Dynamic: keywords
Dynamic: license
Dynamic: license-file
Dynamic: maintainer
Dynamic: maintainer-email
Dynamic: platform
Dynamic: provides-extra
Dynamic: requires-dist
Dynamic: requires-python
Dynamic: summary
